<mxGraphModel dx="800" dy="800" grid="0" guides="1" tooltips="1" connect="1" fold="1" page="1" pageScale="1" pageWidth="826" pageHeight="1169" style="default-style2"><root><mxCell id="0"/><mxCell id="1" parent="0"/><mxCell id="3" value="Database Server" style="strokeWidth=2;shape=mxgraph.er.cloud;buttonText=;fontColor=#000000;fontSize=17;shadow=1;gradientColor=#91E5FF" vertex="1" parent="1"><mxGeometry x="290" y="200" width="370" height="310" as="geometry"/></mxCell><mxCell id="12" value="" style="shape=mxgraph.flowchart.transfer;fillColor=#ffffff;strokeColor=#000000;strokeWidth=2" vertex="1" parent="1"><mxGeometry x="218" y="300" width="97" height="70" as="geometry"/></mxCell><mxCell id="13" value="" style="shape=mxgraph.flowchart.transfer;fillColor=#ffffff;strokeColor=#000000;strokeWidth=2;rotation=180" vertex="1" parent="1"><mxGeometry x="120" y="300" width="97" height="70" as="geometry"/></mxCell><mxCell id="29" value="" style="shape=image;image=http://cdn4.iconfinder.com/data/icons/cc_mono_icon_set/blacks/48x48/server.png" vertex="1" parent="1"><mxGeometry x="330.5" y="325" width="90" height="77.5" as="geometry"/></mxCell><mxCell id="31" value="" style="shape=image;image=http://cdn2.iconfinder.com/data/icons/picol-vector/32/database-128.png" vertex="1" parent="1"><mxGeometry x="420.5" y="275" width="54.5" height="50" as="geometry"/></mxCell><mxCell id="41" value="" style="shape=image;image=http://cdn2.iconfinder.com/data/icons/picol-vector/32/database-128.png" vertex="1" parent="1"><mxGeometry x="495" y="270" width="54.5" height="50" as="geometry"/></mxCell><mxCell id="42" value="" style="shape=image;image=http://cdn2.iconfinder.com/data/icons/picol-vector/32/database-128.png" vertex="1" parent="1"><mxGeometry x="500" y="410" width="54.5" height="50" as="geometry"/></mxCell><mxCell id="44" value="" style="shape=image;image=http://cdn2.iconfinder.com/data/icons/picol-vector/32/database-128.png" vertex="1" parent="1"><mxGeometry x="554.5" y="295" width="54.5" height="50" as="geometry"/></mxCell><mxCell id="45" value="" style="shape=image;image=http://cdn2.iconfinder.com/data/icons/picol-vector/32/database-128.png" vertex="1" parent="1"><mxGeometry x="567.25" y="372.5" width="54.5" height="50" as="geometry"/></mxCell><mxCell id="46" value="" style="shape=image;image=http://cdn2.iconfinder.com/data/icons/picol-vector/32/database-128.png" vertex="1" parent="1"><mxGeometry x="430.5" y="397.5" width="54.5" height="50" as="geometry"/></mxCell><mxCell id="50" value="" style="endArrow=none;entryX=0;entryY=0.5" edge="1" parent="1" source="46" target="42"><mxGeometry relative="1" as="geometry"/></mxCell><mxCell id="51" value="" style="endArrow=none" edge="1" parent="1" source="42" target="45"><mxGeometry relative="1" as="geometry"/></mxCell><mxCell id="52" value="" style="endArrow=none;entryX=0.5;entryY=1" edge="1" parent="1" source="45" target="44"><mxGeometry relative="1" as="geometry"/></mxCell><mxCell id="53" value="" style="endArrow=none" edge="1" parent="1" source="41" target="44"><mxGeometry relative="1" as="geometry"/></mxCell><mxCell id="54" value="" style="endArrow=none" edge="1" parent="1" source="31" target="41"><mxGeometry relative="1" as="geometry"/></mxCell><mxCell id="55" value="" style="endArrow=none;entryX=0.25;entryY=1" edge="1" parent="1" source="42" target="44"><mxGeometry relative="1" as="geometry"/></mxCell><mxCell id="56" value="" style="endArrow=none" edge="1" parent="1" source="42" target="31"><mxGeometry relative="1" as="geometry"/></mxCell><mxCell id="57" value="" style="endArrow=none;entryX=0.5;entryY=1" edge="1" parent="1" source="46" target="41"><mxGeometry relative="1" as="geometry"/></mxCell><mxCell id="58" value="" style="endArrow=none" edge="1" parent="1" source="45" target="29"><mxGeometry relative="1" as="geometry"/></mxCell><mxCell id="59" value="" style="endArrow=none;entryX=0.5;entryY=1" edge="1" parent="1" source="29" target="31"><mxGeometry relative="1" as="geometry"/></mxCell><mxCell id="60" value="" style="endArrow=none;entryX=0;entryY=0.5" edge="1" parent="1" source="29" target="46"><mxGeometry relative="1" as="geometry"/></mxCell></root></mxGraphModel>